OAuth2Util/Demo.py
OAuth2Util/LogDemo.py
OAuth2Util/LongRunDemo.py
OAuth2Util/OAuth2Util.py
OAuth2Util/__init__.py
praw_oauth2util-0.3.5.dist-info/DESCRIPTION.rst
praw_oauth2util-0.3.5.dist-info/METADATA
praw_oauth2util-0.3.5.dist-info/metadata.json
praw_oauth2util-0.3.5.dist-info/RECORD
praw_oauth2util-0.3.5.dist-info/top_level.txt
praw_oauth2util-0.3.5.dist-info/WHEEL
